kaxanuk/data_curator_extensions/yahoo_finance/__init__.py
kaxanuk/data_curator_extensions/yahoo_finance/yahoo_finance.py
kaxanuk_data_curator_extensions_yahoo_finance-0.4.0.dist-info/METADATA
kaxanuk_data_curator_extensions_yahoo_finance-0.4.0.dist-info/WHEEL
kaxanuk_data_curator_extensions_yahoo_finance-0.4.0.dist-info/entry_points.txt
kaxanuk_data_curator_extensions_yahoo_finance-0.4.0.dist-info/licenses/LICENSE
kaxanuk_data_curator_extensions_yahoo_finance-0.4.0.dist-info/RECORD
