Metadata-Version: 2.1
Name: kaxanuk.data_curator_extensions.yahoo_finance
Version: 0.4.0
Summary: Yahoo Finance data provider for the KaxaNuk Data Curator component library
Author-Email: KaxaNuk <info@kaxanuk.mx>, Rinku Kazeno <rinku.kazeno@kaxanuk.mx>, Ruben Flores <ruben.flores@kaxanuk.mx>, Arturo Aguilar <arturo.aguilar@kaxanuk.mx>
License: MIT License
Classifier: Development Status :: 4 - Beta
Classifier: License :: OSI Approved :: MIT License
Classifier: Programming Language :: Python :: 3
Project-URL: Homepage, https://kaxanuk.mx
Project-URL: Repository, https://github.com/KaxaNuk/Data-Curator-Extensions_Yahoo-Finance
Project-URL: Issues, https://github.com/KaxaNuk/Data-Curator-Extensions_Yahoo-Finance/issues
Project-URL: Changelog, https://github.com/KaxaNuk/Data-Curator-Extensions_Yahoo-Finance/blob/main/CHANGELOG.md
Requires-Python: <3.14,>=3.12
Requires-Dist: kaxanuk-data_curator>=0.41.0
Requires-Dist: packaging>=24.2
Requires-Dist: pandas>=2.2.3
Requires-Dist: yfinance>=0.2.65
